tsudo/__init__.py
tsudo/__main__.py
tsudo/tsudo.py
tsudo-0.0.5.data/scripts/tsudo
tsudo-0.0.5.dist-info/METADATA
tsudo-0.0.5.dist-info/RECORD
tsudo-0.0.5.dist-info/WHEEL
tsudo-0.0.5.dist-info/top_level.txt
