Metadata-Version: 2.1
Name: tsudo
Version: 0.0.5
Summary: Tsundere wrapper for sudo command.
Home-page: https://github.com/giovanism/tsudo
Author: Giovan Isa Musthofa
Author-email: giovanism@outlook.co.id
License: WTFPL
Platform: UNKNOWN
Classifier: Programming Language :: Python :: 3
Classifier: Operating System :: Unix
Classifier: Environment :: Console
Classifier: Environment :: Plugins
Classifier: Topic :: System :: Systems Administration
Requires-Python: >3
Requires-Dist: pexpect
